checkers/__init__.py
checkers/board.py
checkers/board_initializer.py
checkers/board_searcher.py
checkers/game.py
checkers/piece.py
test/__init__.py
test/test_game_over.py
test/test_possible_moves.py
test/test_winner.py
imparaai_checkers_for_BFHS_programming-1.4.2.2.dist-info/LICENSE
imparaai_checkers_for_BFHS_programming-1.4.2.2.dist-info/METADATA
imparaai_checkers_for_BFHS_programming-1.4.2.2.dist-info/WHEEL
imparaai_checkers_for_BFHS_programming-1.4.2.2.dist-info/top_level.txt
imparaai_checkers_for_BFHS_programming-1.4.2.2.dist-info/RECORD
