Metadata-Version: 2.1
Name: imparaai-checkers-for-BFHS-programming
Version: 1.4.2.2
Summary: Library for playing a standard game of checkers/draughts
Home-page: https://github.com/Shono1/checkers
Author: Shono1
Author-email: shonor47@gmail.com
License: MIT
Platform: UNKNOWN
Classifier: Programming Language :: Python :: 3
Classifier: License :: OSI Approved :: MIT License
Classifier: Operating System :: OS Independent
